emojisearch
