Metadata-Version: 1.0
Name: emojisearch
Version: 0.2.8
Summary: search emojis using command line
Home-page: https://github.com/keshav11/emoji-search
Author: Keshav Gupta
Author-email: keshav1032@gmail.com
License: MIT
Keywords: emoji cli command-line search emojisearch emoji-search
Platform: UNKNOWN
